pytest_fxa/__init__.py
pytest_fxa/plugin.py
pytest_fxa_mte-1.6.0.dist-info/LICENSE
pytest_fxa_mte-1.6.0.dist-info/METADATA
pytest_fxa_mte-1.6.0.dist-info/WHEEL
pytest_fxa_mte-1.6.0.dist-info/entry_points.txt
pytest_fxa_mte-1.6.0.dist-info/top_level.txt
pytest_fxa_mte-1.6.0.dist-info/RECORD
