Metadata-Version: 2.1
Name: pytest-fxa-mte
Version: 1.6.0
Summary: pytest plugin for Firefox Accounts
Home-page: https://github.com/clarmso/pytest-fxa
Author: Dave Hunt
Author-email: dhunt@mozilla.com
Maintainer: Clare So
Maintainer-email: cso@mozilla.com
License: Mozilla Public License 2.0 (MPL 2.0)
Keywords: py.test pytest mozilla automation firefox account fxa
Classifier: Development Status :: 5 - Production/Stable
Classifier: Framework :: Pytest
Classifier: Intended Audience :: Developers
Classifier: License :: OSI Approved :: Mozilla Public License 2.0 (MPL 2.0)
Classifier: Operating System :: POSIX
Classifier: Operating System :: Microsoft :: Windows
Classifier: Operating System :: MacOS :: MacOS X
Classifier: Topic :: Software Development :: Quality Assurance
Classifier: Topic :: Software Development :: Testing
Classifier: Topic :: Utilities
Classifier: Programming Language :: Python
Classifier: Programming Language :: Python :: 2.7
Classifier: Programming Language :: Python :: 3.6
Classifier: Programming Language :: Python :: 3.7
Classifier: Programming Language :: Python :: Implementation :: CPython
Classifier: Programming Language :: Python :: Implementation :: PyPy
License-File: LICENSE
Requires-Dist: PyFxA
